nginx_analysis/__init__.py
nginx_analysis/analysis.py
nginx_analysis/dataclasses.py
nginx_analysis/filter.py
nginx_analysis/input.py
nginx_analysis/log.py
nginx_analysis/main.py
nginx_analysis/output.py
nginx_static_analysis-0.3.1.dist-info/LICENSE
nginx_static_analysis-0.3.1.dist-info/METADATA
nginx_static_analysis-0.3.1.dist-info/WHEEL
nginx_static_analysis-0.3.1.dist-info/entry_points.txt
nginx_static_analysis-0.3.1.dist-info/top_level.txt
nginx_static_analysis-0.3.1.dist-info/RECORD
