Metadata-Version: 2.1
Name: nginx-static-analysis
Version: 0.3.1
Summary: Parse Nginx configurations in a clear manner for debugging purposes
Home-page: https://github.com/AlexanderGrooff/nginx-static-analysis
Author: Alexander Grooff
Author-email: Alexander Grooff <alexandergrooff@gmail.com>
License: MIT License
Classifier: Programming Language :: Python :: 3
Requires-Python: >=3.7
License-File: LICENSE
Requires-Dist: crossplane ==0.5.7
Requires-Dist: pydantic ==2.7.1
Requires-Dist: loguru ==0.5.3
Requires-Dist: prettytable ==2.5.0
